{"level":"table","context":{"municipality":"MAGANGUE","zone_code":"99","polling_place_code":"05","polling_place_name":"BARRANCA DE YUCA"},"items":[{"table_code":"001","candidate_votes":0,"total_votes":224,"candidate_pct":0.0,"rank_in_table":0,"table_winner":"LIDIO ARTURO GARCIA TURBAY","table_winner_votes":75,"margin_vs_second":36,"top_rivals":[{"name":"LIDIO ARTURO GARCIA TURBAY","votes":75,"pct":33.4821},{"name":"NADYA GEORGETTE BLEL SCAFF","votes":39,"pct":17.4107},{"name":"PACTO HISTÓRICO SENADO","votes":14,"pct":6.25},{"name":"SELMEN DAVID ARANA CANO","votes":14,"pct":6.25},{"name":"ANTONIO JOSE CORREA JIMENEZ","votes":13,"pct":5.8036}]},{"table_code":"002","candidate_votes":0,"total_votes":234,"candidate_pct":0.0,"rank_in_table":0,"table_winner":"LIDIO ARTURO GARCIA TURBAY","table_winner_votes":50,"margin_vs_second":2,"top_rivals":[{"name":"LIDIO ARTURO GARCIA TURBAY","votes":50,"pct":21.3675},{"name":"NADYA GEORGETTE BLEL SCAFF","votes":48,"pct":20.5128},{"name":"VOTOS NULOS NACIONAL","votes":24,"pct":10.2564},{"name":"SELMEN DAVID ARANA CANO","votes":16,"pct":6.8376},{"name":"PACTO HISTÓRICO SENADO","votes":15,"pct":6.4103}]},{"table_code":"003","candidate_votes":0,"total_votes":296,"candidate_pct":0.0,"rank_in_table":0,"table_winner":"LIDIO ARTURO GARCIA TURBAY","table_winner_votes":72,"margin_vs_second":3,"top_rivals":[{"name":"LIDIO ARTURO GARCIA TURBAY","votes":72,"pct":24.3243},{"name":"NADYA GEORGETTE BLEL SCAFF","votes":69,"pct":23.3108},{"name":"SELMEN DAVID ARANA CANO","votes":26,"pct":8.7838},{"name":"VOTOS NULOS NACIONAL","votes":23,"pct":7.7703},{"name":"ANTONIO JOSE CORREA JIMENEZ","votes":12,"pct":4.0541}]},{"table_code":"004","candidate_votes":0,"total_votes":291,"candidate_pct":0.0,"rank_in_table":0,"table_winner":"NADYA GEORGETTE BLEL SCAFF","table_winner_votes":64,"margin_vs_second":6,"top_rivals":[{"name":"NADYA GEORGETTE BLEL SCAFF","votes":64,"pct":21.9931},{"name":"LIDIO ARTURO GARCIA TURBAY","votes":58,"pct":19.9313},{"name":"SELMEN DAVID ARANA CANO","votes":29,"pct":9.9656},{"name":"PACTO HISTÓRICO SENADO","votes":27,"pct":9.2784},{"name":"ANTONIO JOSE CORREA JIMENEZ","votes":18,"pct":6.1856}]},{"table_code":"005","candidate_votes":0,"total_votes":249,"candidate_pct":0.0,"rank_in_table":0,"table_winner":"LIDIO ARTURO GARCIA TURBAY","table_winner_votes":56,"margin_vs_second":34,"top_rivals":[{"name":"LIDIO ARTURO GARCIA TURBAY","votes":56,"pct":22.49},{"name":"NADYA GEORGETTE BLEL SCAFF","votes":56,"pct":22.49},{"name":"SELMEN DAVID ARANA CANO","votes":22,"pct":8.8353},{"name":"PACTO HISTÓRICO SENADO","votes":21,"pct":8.4337},{"name":"ANTONIO JOSE CORREA JIMENEZ","votes":14,"pct":5.6225}]},{"table_code":"006","candidate_votes":0,"total_votes":236,"candidate_pct":0.0,"rank_in_table":0,"table_winner":"NADYA GEORGETTE BLEL SCAFF","table_winner_votes":58,"margin_vs_second":6,"top_rivals":[{"name":"NADYA GEORGETTE BLEL SCAFF","votes":58,"pct":24.5763},{"name":"LIDIO ARTURO GARCIA TURBAY","votes":52,"pct":22.0339},{"name":"SELMEN DAVID ARANA CANO","votes":25,"pct":10.5932},{"name":"ANTONIO JOSE CORREA JIMENEZ","votes":15,"pct":6.3559},{"name":"PACTO HISTÓRICO SENADO","votes":15,"pct":6.3559}]},{"table_code":"007","candidate_votes":0,"total_votes":258,"candidate_pct":0.0,"rank_in_table":0,"table_winner":"LIDIO ARTURO GARCIA TURBAY","table_winner_votes":59,"margin_vs_second":8,"top_rivals":[{"name":"LIDIO ARTURO GARCIA TURBAY","votes":59,"pct":22.8682},{"name":"NADYA GEORGETTE BLEL SCAFF","votes":51,"pct":19.7674},{"name":"SELMEN DAVID ARANA CANO","votes":26,"pct":10.0775},{"name":"PACTO HISTÓRICO SENADO","votes":20,"pct":7.7519},{"name":"ANTONIO JOSE CORREA JIMENEZ","votes":16,"pct":6.2016}]},{"table_code":"008","candidate_votes":0,"total_votes":223,"candidate_pct":0.0,"rank_in_table":0,"table_winner":"NADYA GEORGETTE BLEL SCAFF","table_winner_votes":49,"margin_vs_second":1,"top_rivals":[{"name":"NADYA GEORGETTE BLEL SCAFF","votes":49,"pct":21.9731},{"name":"LIDIO ARTURO GARCIA TURBAY","votes":48,"pct":21.5247},{"name":"SELMEN DAVID ARANA CANO","votes":24,"pct":10.7623},{"name":"PACTO HISTÓRICO SENADO","votes":20,"pct":8.9686},{"name":"ANTONIO JOSE CORREA JIMENEZ","votes":11,"pct":4.9327}]},{"table_code":"009","candidate_votes":0,"total_votes":87,"candidate_pct":0.0,"rank_in_table":0,"table_winner":"LIDIO ARTURO GARCIA TURBAY","table_winner_votes":15,"margin_vs_second":6,"top_rivals":[{"name":"LIDIO ARTURO GARCIA TURBAY","votes":15,"pct":17.2414},{"name":"NADYA GEORGETTE BLEL SCAFF","votes":15,"pct":17.2414},{"name":"JULIO ALBERTO ELIAS VIDAL","votes":9,"pct":10.3448},{"name":"SELMEN DAVID ARANA CANO","votes":9,"pct":10.3448},{"name":"ANTONIO JOSE CORREA JIMENEZ","votes":4,"pct":4.5977}]},{"table_code":"009","candidate_votes":0,"total_votes":87,"candidate_pct":0.0,"rank_in_table":0,"table_winner":"LIDIO ARTURO GARCIA TURBAY","table_winner_votes":15,"margin_vs_second":6,"top_rivals":[{"name":"LIDIO ARTURO GARCIA TURBAY","votes":15,"pct":17.2414},{"name":"NADYA GEORGETTE BLEL SCAFF","votes":15,"pct":17.2414},{"name":"JULIO ALBERTO ELIAS VIDAL","votes":9,"pct":10.3448},{"name":"SELMEN DAVID ARANA CANO","votes":9,"pct":10.3448},{"name":"ANTONIO JOSE CORREA JIMENEZ","votes":4,"pct":4.5977}]}]}