{"level":"polling_place","context":{"municipality":"PUERTO CARREÑO","zone_code":"99"},"items":[{"polling_place_code":"05","polling_place_name":"ACEITICO","candidate_votes":0,"total_votes":49,"candidate_pct":0.0,"tables_total":1,"tables_with_votes":0,"rank_in_place":0,"place_winner":"JUAN CARLOS WILLS OSPINA","place_winner_votes":10},{"polling_place_code":"10","polling_place_name":"CASUARITO","candidate_votes":0,"total_votes":753,"candidate_pct":0.0,"tables_total":5,"tables_with_votes":0,"rank_in_place":0,"place_winner":"JUAN CARLOS GARCES ROJAS","place_winner_votes":160},{"polling_place_code":"40","polling_place_name":"GARCITAS","candidate_votes":0,"total_votes":145,"candidate_pct":0.0,"tables_total":1,"tables_with_votes":0,"rank_in_place":0,"place_winner":"ARIEL FERNANDO AVILA MARTINEZ","place_winner_votes":28},{"polling_place_code":"45","polling_place_name":"GUARIPA","candidate_votes":0,"total_votes":59,"candidate_pct":0.0,"tables_total":1,"tables_with_votes":0,"rank_in_place":0,"place_winner":"ALEJANDRO ALBERTO VEGA PEREZ","place_winner_votes":29},{"polling_place_code":"51","polling_place_name":"LA ESMERALDA","candidate_votes":0,"total_votes":92,"candidate_pct":0.0,"tables_total":1,"tables_with_votes":0,"rank_in_place":0,"place_winner":"PARTIDO CENTRO DEMOCRÁTICO","place_winner_votes":28},{"polling_place_code":"30","polling_place_name":"LA VENTUROSA","candidate_votes":0,"total_votes":107,"candidate_pct":0.0,"tables_total":1,"tables_with_votes":0,"rank_in_place":0,"place_winner":"VOTOS NO MARCADOS NACIONAL","place_winner_votes":19},{"polling_place_code":"50","polling_place_name":"PUERTO MURILLO","candidate_votes":0,"total_votes":43,"candidate_pct":0.0,"tables_total":1,"tables_with_votes":0,"rank_in_place":0,"place_winner":"EDGAR ALFONSO GOMEZ ROMAN","place_winner_votes":5}]}