{"level":"table","context":{"municipality":"FLORENCIA","zone_code":"99","polling_place_code":"71","polling_place_name":"SANTO DOMINGO - VILLA HERMOSA DOS."},"items":[{"table_code":"001","candidate_votes":0,"total_votes":103,"candidate_pct":0.0,"rank_in_table":0,"table_winner":"RICHARD ALFONSO AGUILAR VILLA","table_winner_votes":21,"margin_vs_second":7,"top_rivals":[{"name":"RICHARD ALFONSO AGUILAR VILLA","votes":21,"pct":20.3883},{"name":"PARTIDO CENTRO DEMOCRÁTICO","votes":14,"pct":13.5922},{"name":"JUAN CAMILO OSTOS ROMERO","votes":12,"pct":11.6505},{"name":"VOTOS NO MARCADOS NACIONAL","votes":12,"pct":11.6505},{"name":"PACTO HISTÓRICO SENADO","votes":8,"pct":7.767}]}]}