{"level":"polling_place","context":{"municipality":"SINCE","zone_code":"01"},"items":[{"polling_place_code":"01","polling_place_name":"IE PEDRO ESPINOSA","candidate_votes":14,"total_votes":2565,"candidate_pct":0.5458,"tables_total":12,"tables_with_votes":6,"rank_in_place":19,"place_winner":"HECTOR OLIMPO ESPINOSA OLIVER","place_winner_votes":738},{"polling_place_code":"02","polling_place_name":"I.E. ANTONIO SANTOS","candidate_votes":13,"total_votes":3876,"candidate_pct":0.3354,"tables_total":17,"tables_with_votes":8,"rank_in_place":21,"place_winner":"HECTOR OLIMPO ESPINOSA OLIVER","place_winner_votes":1247}]}