{"level":"table","context":{"municipality":"AGUACHICA","zone_code":"02","polling_place_code":"06","polling_place_name":"SEDE JOSE ANDRES PADILLA CABARCAS"},"items":[{"table_code":"002","candidate_votes":1,"total_votes":143,"candidate_pct":0.6993,"rank_in_table":9,"table_winner":"JOSE ALFREDO GNECCO ZULETA","table_winner_votes":16,"margin_vs_second":3,"top_rivals":[{"name":"JOSE ALFREDO GNECCO ZULETA","votes":16,"pct":11.1888},{"name":"PACTO HISTÓRICO SENADO","votes":13,"pct":9.0909},{"name":"PARTIDO CENTRO DEMOCRÁTICO","votes":11,"pct":7.6923},{"name":"DIDIER LOBO CHINCHILLA","votes":10,"pct":6.993},{"name":"VOTOS NULOS NACIONAL","votes":10,"pct":6.993}]},{"table_code":"001","candidate_votes":0,"total_votes":185,"candidate_pct":0.0,"rank_in_table":0,"table_winner":"PARTIDO CENTRO DEMOCRÁTICO","table_winner_votes":22,"margin_vs_second":4,"top_rivals":[{"name":"PARTIDO CENTRO DEMOCRÁTICO","votes":22,"pct":11.8919},{"name":"PACTO HISTÓRICO SENADO","votes":18,"pct":9.7297},{"name":"VOTOS NO MARCADOS NACIONAL","votes":16,"pct":8.6486},{"name":"JOSE ALFREDO GNECCO ZULETA","votes":14,"pct":7.5676},{"name":"DIDIER LOBO CHINCHILLA","votes":13,"pct":7.027}]}]}