{"level":"table","context":{"municipality":"BOGOTA. D.C.","zone_code":"17","polling_place_code":"03","polling_place_name":"EGIPTO"},"items":[{"table_code":"001","candidate_votes":0,"total_votes":150,"candidate_pct":0.0,"rank_in_table":0,"table_winner":"PACTO HISTÓRICO SENADO","table_winner_votes":45,"margin_vs_second":18,"top_rivals":[{"name":"PACTO HISTÓRICO SENADO","votes":45,"pct":30.0},{"name":"PARTIDO CENTRO DEMOCRÁTICO","votes":27,"pct":18.0},{"name":"VOTOS NO MARCADOS INDIGENAS","votes":8,"pct":5.3333},{"name":"VOTOS NULOS INDIGENAS","votes":7,"pct":4.6667},{"name":"OSCAR HERNAN SANCHEZ LEON","votes":6,"pct":4.0}]},{"table_code":"002","candidate_votes":0,"total_votes":152,"candidate_pct":0.0,"rank_in_table":0,"table_winner":"PACTO HISTÓRICO SENADO","table_winner_votes":54,"margin_vs_second":29,"top_rivals":[{"name":"PACTO HISTÓRICO SENADO","votes":54,"pct":35.5263},{"name":"PARTIDO CENTRO DEMOCRÁTICO","votes":25,"pct":16.4474},{"name":"VOTOS NO MARCADOS NACIONAL","votes":5,"pct":3.2895},{"name":"ALIANZA POR COLOMBIA","votes":4,"pct":2.6316},{"name":"VOTOS NULOS NACIONAL","votes":4,"pct":2.6316}]},{"table_code":"003","candidate_votes":0,"total_votes":154,"candidate_pct":0.0,"rank_in_table":0,"table_winner":"PACTO HISTÓRICO SENADO","table_winner_votes":55,"margin_vs_second":37,"top_rivals":[{"name":"PACTO HISTÓRICO SENADO","votes":55,"pct":35.7143},{"name":"PARTIDO CENTRO DEMOCRÁTICO","votes":18,"pct":11.6883},{"name":"OSCAR HERNAN SANCHEZ LEON","votes":9,"pct":5.8442},{"name":"VOTOS NULOS NACIONAL","votes":6,"pct":3.8961},{"name":"VOTOS EN BLANCO NACIONAL","votes":5,"pct":3.2468}]},{"table_code":"004","candidate_votes":0,"total_votes":184,"candidate_pct":0.0,"rank_in_table":0,"table_winner":"PACTO HISTÓRICO SENADO","table_winner_votes":49,"margin_vs_second":25,"top_rivals":[{"name":"PACTO HISTÓRICO SENADO","votes":49,"pct":26.6304},{"name":"PARTIDO CENTRO DEMOCRÁTICO","votes":24,"pct":13.0435},{"name":"VOTOS NULOS NACIONAL","votes":17,"pct":9.2391},{"name":"VOTOS NO MARCADOS NACIONAL","votes":15,"pct":8.1522},{"name":"ALIANZA POR COLOMBIA","votes":8,"pct":4.3478}]},{"table_code":"005","candidate_votes":0,"total_votes":202,"candidate_pct":0.0,"rank_in_table":0,"table_winner":"PACTO HISTÓRICO SENADO","table_winner_votes":71,"margin_vs_second":42,"top_rivals":[{"name":"PACTO HISTÓRICO SENADO","votes":71,"pct":35.1485},{"name":"PARTIDO CENTRO DEMOCRÁTICO","votes":29,"pct":14.3564},{"name":"OSCAR HERNAN SANCHEZ LEON","votes":10,"pct":4.9505},{"name":"VOTOS NULOS NACIONAL","votes":9,"pct":4.4554},{"name":"JONATHAN FERNEY PULIDO HERNANDEZ","votes":7,"pct":3.4653}]},{"table_code":"006","candidate_votes":0,"total_votes":179,"candidate_pct":0.0,"rank_in_table":0,"table_winner":"PACTO HISTÓRICO SENADO","table_winner_votes":69,"margin_vs_second":46,"top_rivals":[{"name":"PACTO HISTÓRICO SENADO","votes":69,"pct":38.5475},{"name":"PARTIDO CENTRO DEMOCRÁTICO","votes":23,"pct":12.8492},{"name":"VOTOS EN BLANCO NACIONAL","votes":6,"pct":3.352},{"name":"VOTOS NULOS NACIONAL","votes":6,"pct":3.352},{"name":"AHORA COLOMBIA","votes":4,"pct":2.2346}]},{"table_code":"007","candidate_votes":0,"total_votes":174,"candidate_pct":0.0,"rank_in_table":0,"table_winner":"PACTO HISTÓRICO SENADO","table_winner_votes":52,"margin_vs_second":27,"top_rivals":[{"name":"PACTO HISTÓRICO SENADO","votes":52,"pct":29.8851},{"name":"PARTIDO CENTRO DEMOCRÁTICO","votes":25,"pct":14.3678},{"name":"VOTOS EN BLANCO NACIONAL","votes":12,"pct":6.8966},{"name":"VOTOS NULOS NACIONAL","votes":6,"pct":3.4483},{"name":"ARIEL FERNANDO AVILA MARTINEZ","votes":5,"pct":2.8736}]},{"table_code":"008","candidate_votes":0,"total_votes":171,"candidate_pct":0.0,"rank_in_table":0,"table_winner":"PACTO HISTÓRICO SENADO","table_winner_votes":68,"margin_vs_second":36,"top_rivals":[{"name":"PACTO HISTÓRICO SENADO","votes":68,"pct":39.7661},{"name":"PARTIDO CENTRO DEMOCRÁTICO","votes":32,"pct":18.7135},{"name":"VOTOS NULOS INDIGENAS","votes":8,"pct":4.6784},{"name":"VOTOS EN BLANCO INDIGENAS","votes":5,"pct":2.924},{"name":"JOSE NICOLAS GOMEZ MEDINA","votes":4,"pct":2.3392}]},{"table_code":"009","candidate_votes":0,"total_votes":154,"candidate_pct":0.0,"rank_in_table":0,"table_winner":"PACTO HISTÓRICO SENADO","table_winner_votes":59,"margin_vs_second":30,"top_rivals":[{"name":"PACTO HISTÓRICO SENADO","votes":59,"pct":38.3117},{"name":"PARTIDO CENTRO DEMOCRÁTICO","votes":29,"pct":18.8312},{"name":"VOTOS EN BLANCO NACIONAL","votes":4,"pct":2.5974},{"name":"VOTOS NULOS NACIONAL","votes":4,"pct":2.5974},{"name":"ENRIQUE GOMEZ MARTINEZ","votes":3,"pct":1.9481}]},{"table_code":"010","candidate_votes":0,"total_votes":117,"candidate_pct":0.0,"rank_in_table":0,"table_winner":"PACTO HISTÓRICO SENADO","table_winner_votes":47,"margin_vs_second":25,"top_rivals":[{"name":"PACTO HISTÓRICO SENADO","votes":47,"pct":40.1709},{"name":"PARTIDO CENTRO DEMOCRÁTICO","votes":22,"pct":18.8034},{"name":"ALIX YIRLEY VARGAS TORRADO","votes":4,"pct":3.4188},{"name":"MIGUEL ANDRES FORERO BOLIVAR","votes":4,"pct":3.4188},{"name":"VOTOS EN BLANCO NACIONAL","votes":4,"pct":3.4188}]},{"table_code":"011","candidate_votes":0,"total_votes":117,"candidate_pct":0.0,"rank_in_table":0,"table_winner":"PACTO HISTÓRICO SENADO","table_winner_votes":55,"margin_vs_second":47,"top_rivals":[{"name":"PACTO HISTÓRICO SENADO","votes":55,"pct":47.0085},{"name":"VOTOS EN BLANCO NACIONAL","votes":8,"pct":6.8376},{"name":"PARTIDO CENTRO DEMOCRÁTICO","votes":7,"pct":5.9829},{"name":"VOTOS NULOS NACIONAL","votes":4,"pct":3.4188},{"name":"ANDREA PADILLA VILLARRAGA","votes":3,"pct":2.5641}]},{"table_code":"012","candidate_votes":0,"total_votes":131,"candidate_pct":0.0,"rank_in_table":0,"table_winner":"PACTO HISTÓRICO SENADO","table_winner_votes":55,"margin_vs_second":44,"top_rivals":[{"name":"PACTO HISTÓRICO SENADO","votes":55,"pct":41.9847},{"name":"PARTIDO CENTRO DEMOCRÁTICO","votes":11,"pct":8.3969},{"name":"VOTOS EN BLANCO NACIONAL","votes":9,"pct":6.8702},{"name":"LA LISTA DE OVIEDO - CON TODA POR COLOMBIA","votes":4,"pct":3.0534},{"name":"VOTOS NULOS NACIONAL","votes":4,"pct":3.0534}]},{"table_code":"013","candidate_votes":0,"total_votes":133,"candidate_pct":0.0,"rank_in_table":0,"table_winner":"PACTO HISTÓRICO SENADO","table_winner_votes":57,"margin_vs_second":50,"top_rivals":[{"name":"PACTO HISTÓRICO SENADO","votes":57,"pct":42.8571},{"name":"PARTIDO CENTRO DEMOCRÁTICO","votes":7,"pct":5.2632},{"name":"VOTOS EN BLANCO NACIONAL","votes":6,"pct":4.5113},{"name":"MIGUEL ANDRES FORERO BOLIVAR","votes":4,"pct":3.0075},{"name":"OLGA LUCIA VELASQUEZ NIETO","votes":4,"pct":3.0075}]},{"table_code":"014","candidate_votes":0,"total_votes":131,"candidate_pct":0.0,"rank_in_table":0,"table_winner":"PACTO HISTÓRICO SENADO","table_winner_votes":68,"margin_vs_second":61,"top_rivals":[{"name":"PACTO HISTÓRICO SENADO","votes":68,"pct":51.9084},{"name":"VOTOS EN BLANCO NACIONAL","votes":7,"pct":5.3435},{"name":"MIGUEL ANDRES FORERO BOLIVAR","votes":6,"pct":4.5802},{"name":"PARTIDO CENTRO DEMOCRÁTICO","votes":6,"pct":4.5802},{"name":"JONATHAN FERNEY PULIDO HERNANDEZ","votes":4,"pct":3.0534}]},{"table_code":"015","candidate_votes":0,"total_votes":128,"candidate_pct":0.0,"rank_in_table":0,"table_winner":"PACTO HISTÓRICO SENADO","table_winner_votes":64,"margin_vs_second":54,"top_rivals":[{"name":"PACTO HISTÓRICO SENADO","votes":64,"pct":50.0},{"name":"VOTOS EN BLANCO NACIONAL","votes":10,"pct":7.8125},{"name":"HORACIO JOSE SERPA MONCADA","votes":5,"pct":3.9062},{"name":"PARTIDO CENTRO DEMOCRÁTICO","votes":5,"pct":3.9062},{"name":"MARTHA ISABEL PERALTA EPIEYU","votes":3,"pct":2.3438}]},{"table_code":"016","candidate_votes":0,"total_votes":86,"candidate_pct":0.0,"rank_in_table":0,"table_winner":"PACTO HISTÓRICO SENADO","table_winner_votes":36,"margin_vs_second":29,"top_rivals":[{"name":"PACTO HISTÓRICO SENADO","votes":36,"pct":41.8605},{"name":"PARTIDO CENTRO DEMOCRÁTICO","votes":7,"pct":8.1395},{"name":"ARIEL FERNANDO AVILA MARTINEZ","votes":4,"pct":4.6512},{"name":"LA LISTA DE OVIEDO - CON TODA POR COLOMBIA","votes":4,"pct":4.6512},{"name":"VOTOS EN BLANCO NACIONAL","votes":3,"pct":3.4884}]}]}