{"level":"table","context":{"municipality":"BOGOTA. D.C.","zone_code":"12","polling_place_code":"23","polling_place_name":"SAN MIGUEL"},"items":[{"table_code":"005","candidate_votes":1,"total_votes":230,"candidate_pct":0.4348,"rank_in_table":11,"table_winner":"PACTO HISTÓRICO SENADO","table_winner_votes":68,"margin_vs_second":38,"top_rivals":[{"name":"PACTO HISTÓRICO SENADO","votes":68,"pct":29.5652},{"name":"PARTIDO CENTRO DEMOCRÁTICO","votes":30,"pct":13.0435},{"name":"VOTOS EN BLANCO NACIONAL","votes":17,"pct":7.3913},{"name":"JENNIFER DALLEY PEDRAZA SANDOVAL","votes":15,"pct":6.5217},{"name":"LUIS CARLOS RUA SANCHEZ","votes":9,"pct":3.913}]},{"table_code":"001","candidate_votes":0,"total_votes":268,"candidate_pct":0.0,"rank_in_table":0,"table_winner":"PARTIDO CENTRO DEMOCRÁTICO","table_winner_votes":77,"margin_vs_second":17,"top_rivals":[{"name":"PARTIDO CENTRO DEMOCRÁTICO","votes":77,"pct":28.7313},{"name":"PACTO HISTÓRICO SENADO","votes":60,"pct":22.3881},{"name":"ENRIQUE GOMEZ MARTINEZ","votes":9,"pct":3.3582},{"name":"JUAN CARLOS LOZADA VARGAS","votes":8,"pct":2.9851},{"name":"ANGELICA LISBETH LOZANO CORREA","votes":7,"pct":2.6119}]},{"table_code":"002","candidate_votes":0,"total_votes":274,"candidate_pct":0.0,"rank_in_table":0,"table_winner":"PARTIDO CENTRO DEMOCRÁTICO","table_winner_votes":71,"margin_vs_second":22,"top_rivals":[{"name":"PARTIDO CENTRO DEMOCRÁTICO","votes":71,"pct":25.9124},{"name":"PACTO HISTÓRICO SENADO","votes":49,"pct":17.8832},{"name":"ANDREA PADILLA VILLARRAGA","votes":13,"pct":4.7445},{"name":"VOTOS EN BLANCO NACIONAL","votes":13,"pct":4.7445},{"name":"JENNIFER DALLEY PEDRAZA SANDOVAL","votes":8,"pct":2.9197}]},{"table_code":"003","candidate_votes":0,"total_votes":273,"candidate_pct":0.0,"rank_in_table":0,"table_winner":"PACTO HISTÓRICO SENADO","table_winner_votes":65,"margin_vs_second":1,"top_rivals":[{"name":"PACTO HISTÓRICO SENADO","votes":65,"pct":23.8095},{"name":"PARTIDO CENTRO DEMOCRÁTICO","votes":64,"pct":23.4432},{"name":"LA LISTA DE OVIEDO - CON TODA POR COLOMBIA","votes":11,"pct":4.0293},{"name":"ANDREA PADILLA VILLARRAGA","votes":7,"pct":2.5641},{"name":"CARLOS EDUARDO GUEVARA VILLABON","votes":7,"pct":2.5641}]},{"table_code":"004","candidate_votes":0,"total_votes":306,"candidate_pct":0.0,"rank_in_table":0,"table_winner":"PACTO HISTÓRICO SENADO","table_winner_votes":61,"margin_vs_second":27,"top_rivals":[{"name":"PACTO HISTÓRICO SENADO","votes":61,"pct":19.9346},{"name":"ALIANZA POR COLOMBIA","votes":34,"pct":11.1111},{"name":"PARTIDO CENTRO DEMOCRÁTICO","votes":33,"pct":10.7843},{"name":"AHORA COLOMBIA","votes":22,"pct":7.1895},{"name":"PARTIDO LIBERAL COLOMBIANO","votes":14,"pct":4.5752}]},{"table_code":"006","candidate_votes":0,"total_votes":95,"candidate_pct":0.0,"rank_in_table":0,"table_winner":"PACTO HISTÓRICO SENADO","table_winner_votes":17,"margin_vs_second":5,"top_rivals":[{"name":"PACTO HISTÓRICO SENADO","votes":17,"pct":17.8947},{"name":"PARTIDO CENTRO DEMOCRÁTICO","votes":12,"pct":12.6316},{"name":"LUIS CARLOS RUA SANCHEZ","votes":7,"pct":7.3684},{"name":"VOTOS EN BLANCO NACIONAL","votes":7,"pct":7.3684},{"name":"ANDREA PADILLA VILLARRAGA","votes":6,"pct":6.3158}]}]}