{"level":"table","context":{"municipality":"SAN PABLO","zone_code":"00","polling_place_code":"00","polling_place_name":"PUESTO CABECERA MUNICIPAL"},"items":[{"table_code":"030","candidate_votes":1,"total_votes":177,"candidate_pct":0.565,"rank_in_table":10,"table_winner":"LIDIO ARTURO GARCIA TURBAY","table_winner_votes":49,"margin_vs_second":9,"top_rivals":[{"name":"LIDIO ARTURO GARCIA TURBAY","votes":49,"pct":27.6836},{"name":"NADYA GEORGETTE BLEL SCAFF","votes":40,"pct":22.5989},{"name":"PACTO HISTÓRICO SENADO","votes":16,"pct":9.0395},{"name":"ANTONIO JOSE CORREA JIMENEZ","votes":14,"pct":7.9096},{"name":"VOTOS EN BLANCO NACIONAL","votes":6,"pct":3.3898}]},{"table_code":"008","candidate_votes":1,"total_votes":205,"candidate_pct":0.4878,"rank_in_table":11,"table_winner":"NADYA GEORGETTE BLEL SCAFF","table_winner_votes":37,"margin_vs_second":7,"top_rivals":[{"name":"NADYA GEORGETTE BLEL SCAFF","votes":37,"pct":18.0488},{"name":"LIDIO ARTURO GARCIA TURBAY","votes":30,"pct":14.6341},{"name":"PACTO HISTÓRICO SENADO","votes":20,"pct":9.7561},{"name":"ANTONIO JOSE CORREA JIMENEZ","votes":17,"pct":8.2927},{"name":"PARTIDO LIBERAL COLOMBIANO","votes":17,"pct":8.2927}]},{"table_code":"018","candidate_votes":1,"total_votes":227,"candidate_pct":0.4405,"rank_in_table":11,"table_winner":"LIDIO ARTURO GARCIA TURBAY","table_winner_votes":47,"margin_vs_second":1,"top_rivals":[{"name":"LIDIO ARTURO GARCIA TURBAY","votes":47,"pct":20.7048},{"name":"NADYA GEORGETTE BLEL SCAFF","votes":46,"pct":20.2643},{"name":"PACTO HISTÓRICO SENADO","votes":29,"pct":12.7753},{"name":"ANTONIO JOSE CORREA JIMENEZ","votes":18,"pct":7.9295},{"name":"VOTOS NULOS NACIONAL","votes":16,"pct":7.0485}]},{"table_code":"001","candidate_votes":0,"total_votes":166,"candidate_pct":0.0,"rank_in_table":0,"table_winner":"LIDIO ARTURO GARCIA TURBAY","table_winner_votes":35,"margin_vs_second":14,"top_rivals":[{"name":"LIDIO ARTURO GARCIA TURBAY","votes":35,"pct":21.0843},{"name":"NADYA GEORGETTE BLEL SCAFF","votes":21,"pct":12.6506},{"name":"PACTO HISTÓRICO SENADO","votes":18,"pct":10.8434},{"name":"ANTONIO JOSE CORREA JIMENEZ","votes":12,"pct":7.2289},{"name":"VOTOS NO MARCADOS INDIGENAS","votes":11,"pct":6.6265}]},{"table_code":"002","candidate_votes":0,"total_votes":217,"candidate_pct":0.0,"rank_in_table":0,"table_winner":"VOTOS NULOS NACIONAL","table_winner_votes":29,"margin_vs_second":2,"top_rivals":[{"name":"VOTOS NULOS NACIONAL","votes":29,"pct":13.3641},{"name":"PACTO HISTÓRICO SENADO","votes":27,"pct":12.4424},{"name":"NADYA GEORGETTE BLEL SCAFF","votes":26,"pct":11.9816},{"name":"LIDIO ARTURO GARCIA TURBAY","votes":24,"pct":11.0599},{"name":"VOTOS NO MARCADOS NACIONAL","votes":21,"pct":9.6774}]},{"table_code":"003","candidate_votes":0,"total_votes":196,"candidate_pct":0.0,"rank_in_table":0,"table_winner":"LIDIO ARTURO GARCIA TURBAY","table_winner_votes":34,"margin_vs_second":4,"top_rivals":[{"name":"LIDIO ARTURO GARCIA TURBAY","votes":34,"pct":17.3469},{"name":"NADYA GEORGETTE BLEL SCAFF","votes":30,"pct":15.3061},{"name":"PACTO HISTÓRICO SENADO","votes":30,"pct":15.3061},{"name":"VOTOS NULOS NACIONAL","votes":16,"pct":8.1633},{"name":"VOTOS NO MARCADOS NACIONAL","votes":14,"pct":7.1429}]},{"table_code":"003","candidate_votes":0,"total_votes":196,"candidate_pct":0.0,"rank_in_table":0,"table_winner":"LIDIO ARTURO GARCIA TURBAY","table_winner_votes":34,"margin_vs_second":4,"top_rivals":[{"name":"LIDIO ARTURO GARCIA TURBAY","votes":34,"pct":17.3469},{"name":"NADYA GEORGETTE BLEL SCAFF","votes":30,"pct":15.3061},{"name":"PACTO HISTÓRICO SENADO","votes":30,"pct":15.3061},{"name":"VOTOS NULOS NACIONAL","votes":16,"pct":8.1633},{"name":"VOTOS NO MARCADOS NACIONAL","votes":14,"pct":7.1429}]},{"table_code":"004","candidate_votes":0,"total_votes":247,"candidate_pct":0.0,"rank_in_table":0,"table_winner":"LIDIO ARTURO GARCIA TURBAY","table_winner_votes":53,"margin_vs_second":16,"top_rivals":[{"name":"LIDIO ARTURO GARCIA TURBAY","votes":53,"pct":21.4575},{"name":"PACTO HISTÓRICO SENADO","votes":37,"pct":14.9798},{"name":"NADYA GEORGETTE BLEL SCAFF","votes":27,"pct":10.9312},{"name":"VOTOS NO MARCADOS NACIONAL","votes":25,"pct":10.1215},{"name":"PARTIDO LIBERAL COLOMBIANO","votes":19,"pct":7.6923}]},{"table_code":"005","candidate_votes":0,"total_votes":259,"candidate_pct":0.0,"rank_in_table":0,"table_winner":"LIDIO ARTURO GARCIA TURBAY","table_winner_votes":46,"margin_vs_second":10,"top_rivals":[{"name":"LIDIO ARTURO GARCIA TURBAY","votes":46,"pct":17.7606},{"name":"NADYA GEORGETTE BLEL SCAFF","votes":36,"pct":13.8996},{"name":"PACTO HISTÓRICO SENADO","votes":27,"pct":10.4247},{"name":"ANTONIO JOSE CORREA JIMENEZ","votes":20,"pct":7.722},{"name":"PARTIDO LIBERAL COLOMBIANO","votes":18,"pct":6.9498}]},{"table_code":"006","candidate_votes":0,"total_votes":191,"candidate_pct":0.0,"rank_in_table":0,"table_winner":"LIDIO ARTURO GARCIA TURBAY","table_winner_votes":46,"margin_vs_second":14,"top_rivals":[{"name":"LIDIO ARTURO GARCIA TURBAY","votes":46,"pct":24.0838},{"name":"NADYA GEORGETTE BLEL SCAFF","votes":32,"pct":16.7539},{"name":"PACTO HISTÓRICO SENADO","votes":20,"pct":10.4712},{"name":"VOTOS NULOS NACIONAL","votes":18,"pct":9.4241},{"name":"VOTOS NO MARCADOS NACIONAL","votes":13,"pct":6.8063}]},{"table_code":"007","candidate_votes":0,"total_votes":194,"candidate_pct":0.0,"rank_in_table":0,"table_winner":"LIDIO ARTURO GARCIA TURBAY","table_winner_votes":44,"margin_vs_second":16,"top_rivals":[{"name":"LIDIO ARTURO GARCIA TURBAY","votes":44,"pct":22.6804},{"name":"NADYA GEORGETTE BLEL SCAFF","votes":28,"pct":14.433},{"name":"PACTO HISTÓRICO SENADO","votes":20,"pct":10.3093},{"name":"ANTONIO JOSE CORREA JIMENEZ","votes":19,"pct":9.7938},{"name":"VOTOS NO MARCADOS NACIONAL","votes":8,"pct":4.1237}]},{"table_code":"009","candidate_votes":0,"total_votes":212,"candidate_pct":0.0,"rank_in_table":0,"table_winner":"LIDIO ARTURO GARCIA TURBAY","table_winner_votes":38,"margin_vs_second":3,"top_rivals":[{"name":"LIDIO ARTURO GARCIA TURBAY","votes":38,"pct":17.9245},{"name":"NADYA GEORGETTE BLEL SCAFF","votes":35,"pct":16.5094},{"name":"PACTO HISTÓRICO SENADO","votes":28,"pct":13.2075},{"name":"PARTIDO CENTRO DEMOCRÁTICO","votes":15,"pct":7.0755},{"name":"ANTONIO JOSE CORREA JIMENEZ","votes":14,"pct":6.6038}]},{"table_code":"010","candidate_votes":0,"total_votes":223,"candidate_pct":0.0,"rank_in_table":0,"table_winner":"PACTO HISTÓRICO SENADO","table_winner_votes":41,"margin_vs_second":11,"top_rivals":[{"name":"PACTO HISTÓRICO SENADO","votes":41,"pct":18.3857},{"name":"NADYA GEORGETTE BLEL SCAFF","votes":30,"pct":13.4529},{"name":"LIDIO ARTURO GARCIA TURBAY","votes":27,"pct":12.1076},{"name":"VOTOS NULOS NACIONAL","votes":20,"pct":8.9686},{"name":"VOTOS NO MARCADOS NACIONAL","votes":16,"pct":7.1749}]},{"table_code":"011","candidate_votes":0,"total_votes":205,"candidate_pct":0.0,"rank_in_table":0,"table_winner":"LIDIO ARTURO GARCIA TURBAY","table_winner_votes":46,"margin_vs_second":16,"top_rivals":[{"name":"LIDIO ARTURO GARCIA TURBAY","votes":46,"pct":22.439},{"name":"NADYA GEORGETTE BLEL SCAFF","votes":30,"pct":14.6341},{"name":"ANTONIO JOSE CORREA JIMENEZ","votes":21,"pct":10.2439},{"name":"PACTO HISTÓRICO SENADO","votes":21,"pct":10.2439},{"name":"VOTOS NULOS NACIONAL","votes":17,"pct":8.2927}]},{"table_code":"012","candidate_votes":0,"total_votes":204,"candidate_pct":0.0,"rank_in_table":0,"table_winner":"LIDIO ARTURO GARCIA TURBAY","table_winner_votes":45,"margin_vs_second":12,"top_rivals":[{"name":"LIDIO ARTURO GARCIA TURBAY","votes":45,"pct":22.0588},{"name":"NADYA GEORGETTE BLEL SCAFF","votes":33,"pct":16.1765},{"name":"ANTONIO JOSE CORREA JIMENEZ","votes":28,"pct":13.7255},{"name":"PACTO HISTÓRICO SENADO","votes":20,"pct":9.8039},{"name":"PARTIDO CONSERVADOR COLOMBIANO","votes":10,"pct":4.902}]},{"table_code":"013","candidate_votes":0,"total_votes":237,"candidate_pct":0.0,"rank_in_table":0,"table_winner":"LIDIO ARTURO GARCIA TURBAY","table_winner_votes":42,"margin_vs_second":1,"top_rivals":[{"name":"LIDIO ARTURO GARCIA TURBAY","votes":42,"pct":17.7215},{"name":"NADYA GEORGETTE BLEL SCAFF","votes":41,"pct":17.2996},{"name":"PACTO HISTÓRICO SENADO","votes":29,"pct":12.2363},{"name":"VOTOS NULOS NACIONAL","votes":22,"pct":9.2827},{"name":"PARTIDO LIBERAL COLOMBIANO","votes":16,"pct":6.7511}]},{"table_code":"014","candidate_votes":0,"total_votes":248,"candidate_pct":0.0,"rank_in_table":0,"table_winner":"LIDIO ARTURO GARCIA TURBAY","table_winner_votes":50,"margin_vs_second":1,"top_rivals":[{"name":"LIDIO ARTURO GARCIA TURBAY","votes":50,"pct":20.1613},{"name":"NADYA GEORGETTE BLEL SCAFF","votes":49,"pct":19.7581},{"name":"PACTO HISTÓRICO SENADO","votes":24,"pct":9.6774},{"name":"ANTONIO JOSE CORREA JIMENEZ","votes":21,"pct":8.4677},{"name":"VOTOS NO MARCADOS NACIONAL","votes":14,"pct":5.6452}]},{"table_code":"015","candidate_votes":0,"total_votes":244,"candidate_pct":0.0,"rank_in_table":0,"table_winner":"LIDIO ARTURO GARCIA TURBAY","table_winner_votes":44,"margin_vs_second":10,"top_rivals":[{"name":"LIDIO ARTURO GARCIA TURBAY","votes":44,"pct":18.0328},{"name":"NADYA GEORGETTE BLEL SCAFF","votes":34,"pct":13.9344},{"name":"ANTONIO JOSE CORREA JIMENEZ","votes":25,"pct":10.2459},{"name":"PACTO HISTÓRICO SENADO","votes":24,"pct":9.8361},{"name":"VOTOS NULOS NACIONAL","votes":17,"pct":6.9672}]},{"table_code":"016","candidate_votes":0,"total_votes":242,"candidate_pct":0.0,"rank_in_table":0,"table_winner":"LIDIO ARTURO GARCIA TURBAY","table_winner_votes":62,"margin_vs_second":5,"top_rivals":[{"name":"LIDIO ARTURO GARCIA TURBAY","votes":62,"pct":25.6198},{"name":"NADYA GEORGETTE BLEL SCAFF","votes":57,"pct":23.5537},{"name":"ANTONIO JOSE CORREA JIMENEZ","votes":20,"pct":8.2645},{"name":"PACTO HISTÓRICO SENADO","votes":14,"pct":5.7851},{"name":"GUSTAVO ADOLFO MORENO HURTADO","votes":8,"pct":3.3058}]},{"table_code":"017","candidate_votes":0,"total_votes":235,"candidate_pct":0.0,"rank_in_table":0,"table_winner":"NADYA GEORGETTE BLEL SCAFF","table_winner_votes":65,"margin_vs_second":5,"top_rivals":[{"name":"NADYA GEORGETTE BLEL SCAFF","votes":65,"pct":27.6596},{"name":"LIDIO ARTURO GARCIA TURBAY","votes":60,"pct":25.5319},{"name":"ANTONIO JOSE CORREA JIMENEZ","votes":16,"pct":6.8085},{"name":"PACTO HISTÓRICO SENADO","votes":14,"pct":5.9574},{"name":"VOTOS NULOS NACIONAL","votes":14,"pct":5.9574}]},{"table_code":"019","candidate_votes":0,"total_votes":232,"candidate_pct":0.0,"rank_in_table":0,"table_winner":"LIDIO ARTURO GARCIA TURBAY","table_winner_votes":61,"margin_vs_second":24,"top_rivals":[{"name":"LIDIO ARTURO GARCIA TURBAY","votes":61,"pct":26.2931},{"name":"NADYA GEORGETTE BLEL SCAFF","votes":37,"pct":15.9483},{"name":"PACTO HISTÓRICO SENADO","votes":32,"pct":13.7931},{"name":"VOTOS NULOS NACIONAL","votes":19,"pct":8.1897},{"name":"ANTONIO JOSE CORREA JIMENEZ","votes":15,"pct":6.4655}]},{"table_code":"020","candidate_votes":0,"total_votes":221,"candidate_pct":0.0,"rank_in_table":0,"table_winner":"NADYA GEORGETTE BLEL SCAFF","table_winner_votes":61,"margin_vs_second":12,"top_rivals":[{"name":"NADYA GEORGETTE BLEL SCAFF","votes":61,"pct":27.6018},{"name":"LIDIO ARTURO GARCIA TURBAY","votes":49,"pct":22.1719},{"name":"ANTONIO JOSE CORREA JIMENEZ","votes":22,"pct":9.9548},{"name":"PACTO HISTÓRICO SENADO","votes":17,"pct":7.6923},{"name":"PARTIDO CENTRO DEMOCRÁTICO","votes":8,"pct":3.6199}]},{"table_code":"021","candidate_votes":0,"total_votes":212,"candidate_pct":0.0,"rank_in_table":0,"table_winner":"LIDIO ARTURO GARCIA TURBAY","table_winner_votes":49,"margin_vs_second":7,"top_rivals":[{"name":"LIDIO ARTURO GARCIA TURBAY","votes":49,"pct":23.1132},{"name":"NADYA GEORGETTE BLEL SCAFF","votes":42,"pct":19.8113},{"name":"PACTO HISTÓRICO SENADO","votes":24,"pct":11.3208},{"name":"ANTONIO JOSE CORREA JIMENEZ","votes":23,"pct":10.8491},{"name":"VOTOS NO MARCADOS NACIONAL","votes":11,"pct":5.1887}]},{"table_code":"022","candidate_votes":0,"total_votes":210,"candidate_pct":0.0,"rank_in_table":0,"table_winner":"NADYA GEORGETTE BLEL SCAFF","table_winner_votes":40,"margin_vs_second":4,"top_rivals":[{"name":"NADYA GEORGETTE BLEL SCAFF","votes":40,"pct":19.0476},{"name":"LIDIO ARTURO GARCIA TURBAY","votes":36,"pct":17.1429},{"name":"PACTO HISTÓRICO SENADO","votes":29,"pct":13.8095},{"name":"ANTONIO JOSE CORREA JIMENEZ","votes":20,"pct":9.5238},{"name":"VOTOS NO MARCADOS NACIONAL","votes":18,"pct":8.5714}]},{"table_code":"023","candidate_votes":0,"total_votes":207,"candidate_pct":0.0,"rank_in_table":0,"table_winner":"PACTO HISTÓRICO SENADO","table_winner_votes":34,"margin_vs_second":1,"top_rivals":[{"name":"PACTO HISTÓRICO SENADO","votes":34,"pct":16.4251},{"name":"LIDIO ARTURO GARCIA TURBAY","votes":33,"pct":15.942},{"name":"NADYA GEORGETTE BLEL SCAFF","votes":31,"pct":14.9758},{"name":"PARTIDO CENTRO DEMOCRÁTICO","votes":25,"pct":12.0773},{"name":"ANTONIO JOSE CORREA JIMENEZ","votes":17,"pct":8.2126}]},{"table_code":"024","candidate_votes":0,"total_votes":224,"candidate_pct":0.0,"rank_in_table":0,"table_winner":"NADYA GEORGETTE BLEL SCAFF","table_winner_votes":48,"margin_vs_second":10,"top_rivals":[{"name":"NADYA GEORGETTE BLEL SCAFF","votes":48,"pct":21.4286},{"name":"LIDIO ARTURO GARCIA TURBAY","votes":38,"pct":16.9643},{"name":"PACTO HISTÓRICO SENADO","votes":31,"pct":13.8393},{"name":"VOTOS NULOS NACIONAL","votes":16,"pct":7.1429},{"name":"VOTOS NO MARCADOS NACIONAL","votes":14,"pct":6.25}]},{"table_code":"025","candidate_votes":0,"total_votes":199,"candidate_pct":0.0,"rank_in_table":0,"table_winner":"LIDIO ARTURO GARCIA TURBAY","table_winner_votes":39,"margin_vs_second":8,"top_rivals":[{"name":"LIDIO ARTURO GARCIA TURBAY","votes":39,"pct":19.598},{"name":"NADYA GEORGETTE BLEL SCAFF","votes":31,"pct":15.5779},{"name":"ANTONIO JOSE CORREA JIMENEZ","votes":23,"pct":11.5578},{"name":"PACTO HISTÓRICO SENADO","votes":22,"pct":11.0553},{"name":"VOTOS NULOS NACIONAL","votes":14,"pct":7.0352}]},{"table_code":"026","candidate_votes":0,"total_votes":183,"candidate_pct":0.0,"rank_in_table":0,"table_winner":"LIDIO ARTURO GARCIA TURBAY","table_winner_votes":51,"margin_vs_second":23,"top_rivals":[{"name":"LIDIO ARTURO GARCIA TURBAY","votes":51,"pct":27.8689},{"name":"NADYA GEORGETTE BLEL SCAFF","votes":28,"pct":15.3005},{"name":"PACTO HISTÓRICO SENADO","votes":18,"pct":9.8361},{"name":"ANTONIO JOSE CORREA JIMENEZ","votes":17,"pct":9.2896},{"name":"PARTIDO CONSERVADOR COLOMBIANO","votes":8,"pct":4.3716}]},{"table_code":"027","candidate_votes":0,"total_votes":187,"candidate_pct":0.0,"rank_in_table":0,"table_winner":"LIDIO ARTURO GARCIA TURBAY","table_winner_votes":51,"margin_vs_second":11,"top_rivals":[{"name":"LIDIO ARTURO GARCIA TURBAY","votes":51,"pct":27.2727},{"name":"NADYA GEORGETTE BLEL SCAFF","votes":40,"pct":21.3904},{"name":"ANTONIO JOSE CORREA JIMENEZ","votes":17,"pct":9.0909},{"name":"PACTO HISTÓRICO SENADO","votes":14,"pct":7.4866},{"name":"VOTOS EN BLANCO NACIONAL","votes":6,"pct":3.2086}]},{"table_code":"028","candidate_votes":0,"total_votes":192,"candidate_pct":0.0,"rank_in_table":0,"table_winner":"LIDIO ARTURO GARCIA TURBAY","table_winner_votes":52,"margin_vs_second":11,"top_rivals":[{"name":"LIDIO ARTURO GARCIA TURBAY","votes":52,"pct":27.0833},{"name":"NADYA GEORGETTE BLEL SCAFF","votes":41,"pct":21.3542},{"name":"PACTO HISTÓRICO SENADO","votes":23,"pct":11.9792},{"name":"ANTONIO JOSE CORREA JIMENEZ","votes":14,"pct":7.2917},{"name":"DAVID ALEJANDRO BARGUIL ASSIS","votes":5,"pct":2.6042}]},{"table_code":"029","candidate_votes":0,"total_votes":191,"candidate_pct":0.0,"rank_in_table":0,"table_winner":"LIDIO ARTURO GARCIA TURBAY","table_winner_votes":59,"margin_vs_second":22,"top_rivals":[{"name":"LIDIO ARTURO GARCIA TURBAY","votes":59,"pct":30.8901},{"name":"NADYA GEORGETTE BLEL SCAFF","votes":37,"pct":19.3717},{"name":"ANTONIO JOSE CORREA JIMENEZ","votes":21,"pct":10.9948},{"name":"PACTO HISTÓRICO SENADO","votes":21,"pct":10.9948},{"name":"NELSON JAVIER LOPEZ RODRIGUEZ","votes":7,"pct":3.6649}]},{"table_code":"031","candidate_votes":0,"total_votes":179,"candidate_pct":0.0,"rank_in_table":0,"table_winner":"LIDIO ARTURO GARCIA TURBAY","table_winner_votes":54,"margin_vs_second":23,"top_rivals":[{"name":"LIDIO ARTURO GARCIA TURBAY","votes":54,"pct":30.1676},{"name":"NADYA GEORGETTE BLEL SCAFF","votes":31,"pct":17.3184},{"name":"ANTONIO JOSE CORREA JIMENEZ","votes":18,"pct":10.0559},{"name":"PACTO HISTÓRICO SENADO","votes":16,"pct":8.9385},{"name":"VOTOS NULOS NACIONAL","votes":9,"pct":5.0279}]},{"table_code":"032","candidate_votes":0,"total_votes":167,"candidate_pct":0.0,"rank_in_table":0,"table_winner":"NADYA GEORGETTE BLEL SCAFF","table_winner_votes":36,"margin_vs_second":4,"top_rivals":[{"name":"NADYA GEORGETTE BLEL SCAFF","votes":36,"pct":21.5569},{"name":"LIDIO ARTURO GARCIA TURBAY","votes":32,"pct":19.1617},{"name":"PACTO HISTÓRICO SENADO","votes":19,"pct":11.3772},{"name":"ANTONIO JOSE CORREA JIMENEZ","votes":14,"pct":8.3832},{"name":"PARTIDO LIBERAL COLOMBIANO","votes":7,"pct":4.1916}]},{"table_code":"033","candidate_votes":0,"total_votes":188,"candidate_pct":0.0,"rank_in_table":0,"table_winner":"NADYA GEORGETTE BLEL SCAFF","table_winner_votes":42,"margin_vs_second":5,"top_rivals":[{"name":"NADYA GEORGETTE BLEL SCAFF","votes":42,"pct":22.3404},{"name":"LIDIO ARTURO GARCIA TURBAY","votes":37,"pct":19.6809},{"name":"PACTO HISTÓRICO SENADO","votes":19,"pct":10.1064},{"name":"ANTONIO JOSE CORREA JIMENEZ","votes":13,"pct":6.9149},{"name":"VOTOS NULOS NACIONAL","votes":11,"pct":5.8511}]},{"table_code":"034","candidate_votes":0,"total_votes":214,"candidate_pct":0.0,"rank_in_table":0,"table_winner":"LIDIO ARTURO GARCIA TURBAY","table_winner_votes":51,"margin_vs_second":5,"top_rivals":[{"name":"LIDIO ARTURO GARCIA TURBAY","votes":51,"pct":23.8318},{"name":"NADYA GEORGETTE BLEL SCAFF","votes":46,"pct":21.4953},{"name":"ANTONIO JOSE CORREA JIMENEZ","votes":19,"pct":8.8785},{"name":"PACTO HISTÓRICO SENADO","votes":15,"pct":7.0093},{"name":"VOTOS NULOS NACIONAL","votes":14,"pct":6.5421}]},{"table_code":"035","candidate_votes":0,"total_votes":191,"candidate_pct":0.0,"rank_in_table":0,"table_winner":"LIDIO ARTURO GARCIA TURBAY","table_winner_votes":47,"margin_vs_second":7,"top_rivals":[{"name":"LIDIO ARTURO GARCIA TURBAY","votes":47,"pct":24.6073},{"name":"NADYA GEORGETTE BLEL SCAFF","votes":40,"pct":20.9424},{"name":"PACTO HISTÓRICO SENADO","votes":21,"pct":10.9948},{"name":"ANTONIO JOSE CORREA JIMENEZ","votes":17,"pct":8.9005},{"name":"VOTOS NO MARCADOS NACIONAL","votes":6,"pct":3.1414}]},{"table_code":"036","candidate_votes":0,"total_votes":201,"candidate_pct":0.0,"rank_in_table":0,"table_winner":"LIDIO ARTURO GARCIA TURBAY","table_winner_votes":58,"margin_vs_second":9,"top_rivals":[{"name":"LIDIO ARTURO GARCIA TURBAY","votes":58,"pct":28.8557},{"name":"NADYA GEORGETTE BLEL SCAFF","votes":49,"pct":24.3781},{"name":"PACTO HISTÓRICO SENADO","votes":22,"pct":10.9453},{"name":"ANTONIO JOSE CORREA JIMENEZ","votes":10,"pct":4.9751},{"name":"VOTOS NULOS NACIONAL","votes":9,"pct":4.4776}]},{"table_code":"037","candidate_votes":0,"total_votes":197,"candidate_pct":0.0,"rank_in_table":0,"table_winner":"NADYA GEORGETTE BLEL SCAFF","table_winner_votes":53,"margin_vs_second":19,"top_rivals":[{"name":"NADYA GEORGETTE BLEL SCAFF","votes":53,"pct":26.9036},{"name":"LIDIO ARTURO GARCIA TURBAY","votes":34,"pct":17.2589},{"name":"ANTONIO JOSE CORREA JIMENEZ","votes":26,"pct":13.198},{"name":"PACTO HISTÓRICO SENADO","votes":16,"pct":8.1218},{"name":"VOTOS NULOS NACIONAL","votes":8,"pct":4.0609}]},{"table_code":"038","candidate_votes":0,"total_votes":204,"candidate_pct":0.0,"rank_in_table":0,"table_winner":"LIDIO ARTURO GARCIA TURBAY","table_winner_votes":47,"margin_vs_second":1,"top_rivals":[{"name":"LIDIO ARTURO GARCIA TURBAY","votes":47,"pct":23.0392},{"name":"NADYA GEORGETTE BLEL SCAFF","votes":46,"pct":22.549},{"name":"PACTO HISTÓRICO SENADO","votes":28,"pct":13.7255},{"name":"ANTONIO JOSE CORREA JIMENEZ","votes":26,"pct":12.7451},{"name":"VOTOS NULOS NACIONAL","votes":11,"pct":5.3922}]},{"table_code":"039","candidate_votes":0,"total_votes":209,"candidate_pct":0.0,"rank_in_table":0,"table_winner":"LIDIO ARTURO GARCIA TURBAY","table_winner_votes":63,"margin_vs_second":19,"top_rivals":[{"name":"LIDIO ARTURO GARCIA TURBAY","votes":63,"pct":30.1435},{"name":"NADYA GEORGETTE BLEL SCAFF","votes":44,"pct":21.0526},{"name":"ANTONIO JOSE CORREA JIMENEZ","votes":24,"pct":11.4833},{"name":"PACTO HISTÓRICO SENADO","votes":15,"pct":7.177},{"name":"VOTOS NULOS NACIONAL","votes":7,"pct":3.3493}]},{"table_code":"040","candidate_votes":0,"total_votes":204,"candidate_pct":0.0,"rank_in_table":0,"table_winner":"LIDIO ARTURO GARCIA TURBAY","table_winner_votes":58,"margin_vs_second":14,"top_rivals":[{"name":"LIDIO ARTURO GARCIA TURBAY","votes":58,"pct":28.4314},{"name":"NADYA GEORGETTE BLEL SCAFF","votes":44,"pct":21.5686},{"name":"PACTO HISTÓRICO SENADO","votes":24,"pct":11.7647},{"name":"ANTONIO JOSE CORREA JIMENEZ","votes":20,"pct":9.8039},{"name":"VOTOS NULOS NACIONAL","votes":6,"pct":2.9412}]},{"table_code":"041","candidate_votes":0,"total_votes":214,"candidate_pct":0.0,"rank_in_table":0,"table_winner":"LIDIO ARTURO GARCIA TURBAY","table_winner_votes":55,"margin_vs_second":14,"top_rivals":[{"name":"LIDIO ARTURO GARCIA TURBAY","votes":55,"pct":25.7009},{"name":"NADYA GEORGETTE BLEL SCAFF","votes":41,"pct":19.1589},{"name":"ANTONIO JOSE CORREA JIMENEZ","votes":26,"pct":12.1495},{"name":"PACTO HISTÓRICO SENADO","votes":18,"pct":8.4112},{"name":"NELSON JAVIER LOPEZ RODRIGUEZ","votes":8,"pct":3.7383}]},{"table_code":"042","candidate_votes":0,"total_votes":201,"candidate_pct":0.0,"rank_in_table":0,"table_winner":"LIDIO ARTURO GARCIA TURBAY","table_winner_votes":49,"margin_vs_second":6,"top_rivals":[{"name":"LIDIO ARTURO GARCIA TURBAY","votes":49,"pct":24.3781},{"name":"NADYA GEORGETTE BLEL SCAFF","votes":43,"pct":21.393},{"name":"PACTO HISTÓRICO SENADO","votes":26,"pct":12.9353},{"name":"ANTONIO JOSE CORREA JIMENEZ","votes":20,"pct":9.9502},{"name":"NELSON JAVIER LOPEZ RODRIGUEZ","votes":8,"pct":3.9801}]},{"table_code":"043","candidate_votes":0,"total_votes":203,"candidate_pct":0.0,"rank_in_table":0,"table_winner":"LIDIO ARTURO GARCIA TURBAY","table_winner_votes":46,"margin_vs_second":3,"top_rivals":[{"name":"LIDIO ARTURO GARCIA TURBAY","votes":46,"pct":22.6601},{"name":"NADYA GEORGETTE BLEL SCAFF","votes":43,"pct":21.1823},{"name":"ANTONIO JOSE CORREA JIMENEZ","votes":23,"pct":11.33},{"name":"PACTO HISTÓRICO SENADO","votes":20,"pct":9.8522},{"name":"VOTOS NULOS NACIONAL","votes":12,"pct":5.9113}]},{"table_code":"044","candidate_votes":0,"total_votes":179,"candidate_pct":0.0,"rank_in_table":0,"table_winner":"LIDIO ARTURO GARCIA TURBAY","table_winner_votes":48,"margin_vs_second":5,"top_rivals":[{"name":"LIDIO ARTURO GARCIA TURBAY","votes":48,"pct":26.8156},{"name":"NADYA GEORGETTE BLEL SCAFF","votes":43,"pct":24.0223},{"name":"PACTO HISTÓRICO SENADO","votes":18,"pct":10.0559},{"name":"ANTONIO JOSE CORREA JIMENEZ","votes":10,"pct":5.5866},{"name":"VOTOS NULOS NACIONAL","votes":8,"pct":4.4693}]},{"table_code":"045","candidate_votes":0,"total_votes":203,"candidate_pct":0.0,"rank_in_table":0,"table_winner":"LIDIO ARTURO GARCIA TURBAY","table_winner_votes":48,"margin_vs_second":3,"top_rivals":[{"name":"LIDIO ARTURO GARCIA TURBAY","votes":48,"pct":23.6453},{"name":"NADYA GEORGETTE BLEL SCAFF","votes":45,"pct":22.1675},{"name":"PACTO HISTÓRICO SENADO","votes":27,"pct":13.3005},{"name":"VOTOS NULOS NACIONAL","votes":18,"pct":8.867},{"name":"ANTONIO JOSE CORREA JIMENEZ","votes":13,"pct":6.4039}]},{"table_code":"046","candidate_votes":0,"total_votes":182,"candidate_pct":0.0,"rank_in_table":0,"table_winner":"LIDIO ARTURO GARCIA TURBAY","table_winner_votes":55,"margin_vs_second":22,"top_rivals":[{"name":"LIDIO ARTURO GARCIA TURBAY","votes":55,"pct":30.2198},{"name":"NADYA GEORGETTE BLEL SCAFF","votes":33,"pct":18.1319},{"name":"ANTONIO JOSE CORREA JIMENEZ","votes":22,"pct":12.0879},{"name":"PACTO HISTÓRICO SENADO","votes":17,"pct":9.3407},{"name":"DAVID ALEJANDRO BARGUIL ASSIS","votes":8,"pct":4.3956}]},{"table_code":"047","candidate_votes":0,"total_votes":193,"candidate_pct":0.0,"rank_in_table":0,"table_winner":"NADYA GEORGETTE BLEL SCAFF","table_winner_votes":46,"margin_vs_second":1,"top_rivals":[{"name":"NADYA GEORGETTE BLEL SCAFF","votes":46,"pct":23.8342},{"name":"LIDIO ARTURO GARCIA TURBAY","votes":45,"pct":23.3161},{"name":"ANTONIO JOSE CORREA JIMENEZ","votes":28,"pct":14.5078},{"name":"PACTO HISTÓRICO SENADO","votes":22,"pct":11.399},{"name":"VOTOS NULOS NACIONAL","votes":5,"pct":2.5907}]},{"table_code":"048","candidate_votes":0,"total_votes":200,"candidate_pct":0.0,"rank_in_table":0,"table_winner":"LIDIO ARTURO GARCIA TURBAY","table_winner_votes":52,"margin_vs_second":16,"top_rivals":[{"name":"LIDIO ARTURO GARCIA TURBAY","votes":52,"pct":26.0},{"name":"NADYA GEORGETTE BLEL SCAFF","votes":36,"pct":18.0},{"name":"ANTONIO JOSE CORREA JIMENEZ","votes":21,"pct":10.5},{"name":"PACTO HISTÓRICO SENADO","votes":19,"pct":9.5},{"name":"VOTOS EN BLANCO NACIONAL","votes":9,"pct":4.5}]},{"table_code":"049","candidate_votes":0,"total_votes":185,"candidate_pct":0.0,"rank_in_table":0,"table_winner":"LIDIO ARTURO GARCIA TURBAY","table_winner_votes":51,"margin_vs_second":15,"top_rivals":[{"name":"LIDIO ARTURO GARCIA TURBAY","votes":51,"pct":27.5676},{"name":"NADYA GEORGETTE BLEL SCAFF","votes":36,"pct":19.4595},{"name":"PACTO HISTÓRICO SENADO","votes":22,"pct":11.8919},{"name":"ANTONIO JOSE CORREA JIMENEZ","votes":12,"pct":6.4865},{"name":"PARTIDO CENTRO DEMOCRÁTICO","votes":6,"pct":3.2432}]},{"table_code":"050","candidate_votes":0,"total_votes":194,"candidate_pct":0.0,"rank_in_table":0,"table_winner":"LIDIO ARTURO GARCIA TURBAY","table_winner_votes":44,"margin_vs_second":1,"top_rivals":[{"name":"LIDIO ARTURO GARCIA TURBAY","votes":44,"pct":22.6804},{"name":"NADYA GEORGETTE BLEL SCAFF","votes":43,"pct":22.1649},{"name":"PACTO HISTÓRICO SENADO","votes":26,"pct":13.4021},{"name":"ANTONIO JOSE CORREA JIMENEZ","votes":15,"pct":7.732},{"name":"PARTIDO CENTRO DEMOCRÁTICO","votes":8,"pct":4.1237}]},{"table_code":"051","candidate_votes":0,"total_votes":199,"candidate_pct":0.0,"rank_in_table":0,"table_winner":"LIDIO ARTURO GARCIA TURBAY","table_winner_votes":65,"margin_vs_second":40,"top_rivals":[{"name":"LIDIO ARTURO GARCIA TURBAY","votes":65,"pct":32.6633},{"name":"NADYA GEORGETTE BLEL SCAFF","votes":25,"pct":12.5628},{"name":"ANTONIO JOSE CORREA JIMENEZ","votes":20,"pct":10.0503},{"name":"PACTO HISTÓRICO SENADO","votes":20,"pct":10.0503},{"name":"VOTOS NULOS NACIONAL","votes":9,"pct":4.5226}]},{"table_code":"052","candidate_votes":0,"total_votes":170,"candidate_pct":0.0,"rank_in_table":0,"table_winner":"LIDIO ARTURO GARCIA TURBAY","table_winner_votes":43,"margin_vs_second":7,"top_rivals":[{"name":"LIDIO ARTURO GARCIA TURBAY","votes":43,"pct":25.2941},{"name":"NADYA GEORGETTE BLEL SCAFF","votes":36,"pct":21.1765},{"name":"ANTONIO JOSE CORREA JIMENEZ","votes":17,"pct":10.0},{"name":"PACTO HISTÓRICO SENADO","votes":10,"pct":5.8824},{"name":"PARTIDO CONSERVADOR COLOMBIANO","votes":8,"pct":4.7059}]},{"table_code":"053","candidate_votes":0,"total_votes":198,"candidate_pct":0.0,"rank_in_table":0,"table_winner":"LIDIO ARTURO GARCIA TURBAY","table_winner_votes":44,"margin_vs_second":7,"top_rivals":[{"name":"LIDIO ARTURO GARCIA TURBAY","votes":44,"pct":22.2222},{"name":"NADYA GEORGETTE BLEL SCAFF","votes":37,"pct":18.6869},{"name":"ANTONIO JOSE CORREA JIMENEZ","votes":22,"pct":11.1111},{"name":"PACTO HISTÓRICO SENADO","votes":14,"pct":7.0707},{"name":"VOTOS NULOS NACIONAL","votes":12,"pct":6.0606}]},{"table_code":"054","candidate_votes":0,"total_votes":9,"candidate_pct":0.0,"rank_in_table":0,"table_winner":"PACTO HISTÓRICO SENADO","table_winner_votes":4,"margin_vs_second":2,"top_rivals":[{"name":"PACTO HISTÓRICO SENADO","votes":4,"pct":44.4444},{"name":"LIDIO ARTURO GARCIA TURBAY","votes":2,"pct":22.2222},{"name":"ENRIQUE GOMEZ MARTINEZ","votes":1,"pct":11.1111},{"name":"GUSTAVO ADOLFO MORENO HURTADO","votes":1,"pct":11.1111},{"name":"PARTIDO LIBERAL COLOMBIANO","votes":1,"pct":11.1111}]}]}